MANIFEST.in
NEWS
README.txt
setup.py
docs/index.html
docs/regularsmooth.html
examples/smoothing_constrained.py
examples/smoothing_ordered.py
examples/smoothing_scattered.py
scikits/__init__.py
scikits.datasmooth.egg-info/PKG-INFO
scikits.datasmooth.egg-info/SOURCES.txt
scikits.datasmooth.egg-info/dependency_links.txt
scikits.datasmooth.egg-info/namespace_packages.txt
scikits.datasmooth.egg-info/top_level.txt
scikits.datasmooth.egg-info/zip-safe
scikits/datasmooth/__init__.py
scikits/datasmooth/regularsmooth.py